{
  "db_name": "PostgreSQL",
  "query": "\n        SELECT \n            id,\n            name,\n            full_description,\n            start_date,\n            end_date,\n            location,\n            original_location,\n            google_place_id,\n            location_name,\n            event_type as \"event_type: EventType\",\n            url,\n            confidence\n        FROM app.events\n        WHERE start_date = $1 \n          AND end_date IS NOT DISTINCT FROM $2\n          AND location IS NOT DISTINCT FROM $3\n        ",
  "describe": {
    "columns": [
      {
        "ordinal": 0,
        "name": "id",
        "type_info": "Int8"
      },
      {
        "ordinal": 1,
        "name": "name",
        "type_info": "Text"
      },
      {
        "ordinal": 2,
        "name": "full_description",
        "type_info": "Text"
      },
      {
        "ordinal": 3,
        "name": "start_date",
        "type_info": "Timestamptz"
      },
      {
        "ordinal": 4,
        "name": "end_date",
        "type_info": "Timestamptz"
      },
      {
        "ordinal": 5,
        "name": "location",
        "type_info": "Text"
      },
      {
        "ordinal": 6,
        "name": "original_location",
        "type_info": "Text"
      },
      {
        "ordinal": 7,
        "name": "google_place_id",
        "type_info": "Text"
      },
      {
        "ordinal": 8,
        "name": "location_name",
        "type_info": "Text"
      },
      {
        "ordinal": 9,
        "name": "event_type: EventType",
        "type_info": {
          "Custom": {
            "name": "app.event_type",
            "kind": {
              "Enum": [
                "YardSale",
                "Art",
                "Music",
                "Dance",
                "Performance",
                "Food",
                "PersonalService",
                "Meeting",
                "Government",
                "Volunteer",
                "Fundraiser",
                "Film",
                "Theater",
                "Comedy",
                "Literature",
                "Exhibition",
                "Workshop",
                "Fitness",
                "Market",
                "Sports",
                "Family",
                "Social",
                "Holiday",
                "Religious",
                "Other"
              ]
            }
          }
        }
      },
      {
        "ordinal": 10,
        "name": "url",
        "type_info": "Text"
      },
      {
        "ordinal": 11,
        "name": "confidence",
        "type_info": "Float8"
      }
    ],
    "parameters": {
      "Left": [
        "Timestamptz",
        "Timestamptz",
        "Text"
      ]
    },
    "nullable": [
      false,
      false,
      false,
      false,
      true,
      true,
      true,
      true,
      true,
      true,
      true,
      false
    ]
  },
  "hash": "58cacda50956596dfa9d825b9cc16e98dedeba80f6c520fba03a365676d0a355"
}
